{
    "title": "YouthHarvest Dashboard Documentation",
    "overview": "\n    The YouthHarvest Dashboard is an interactive tool designed to help young Nigerian entrepreneurs identify \n    opportunities in the post-harvest sector. It visualizes post-harvest loss data across different crops, \n    states, and value chain stages, and recommends appropriate business models based on local conditions \n    and user preferences.\n    ",
    "components": [
        {
            "name": "Interactive Dashboard",
            "description": "Web-based interface for exploring PHL data and business opportunities",
            "features": [
                "Filtering by region, crop, and investment capacity",
                "Visualizations of key PHL metrics",
                "Business opportunity recommendations",
                "Links to implementation guides"
            ],
            "technologies": "HTML, CSS, JavaScript (would use React in full implementation)"
        },
        {
            "name": "Data API",
            "description": "Backend services for accessing and filtering PHL and business opportunity data",
            "features": [
                "RESTful endpoints for different data views",
                "Filtering and query capabilities",
                "JSON response format"
            ],
            "technologies": "Would be implemented with Node.js/Express or Python Flask in production"
        },
        {
            "name": "Implementation Guide Integration",
            "description": "Connection to detailed business model implementation guides",
            "features": [
                "Access to business model details based on user selections",
                "Customized recommendations based on location and preferences",
                "Financial calculator integration"
            ]
        }
    ],
    "usage_instructions": [
        {
            "step": "1. Select Your Region",
            "description": "Use the region filter to focus on your state or geopolitical zone"
        },
        {
            "step": "2. Explore PHL Patterns",
            "description": "Review the visualizations to understand where losses are occurring in your region"
        },
        {
            "step": "3. Filter by Crop Interest",
            "description": "Select specific crops you're interested in working with"
        },
        {
            "step": "4. Review Business Opportunities",
            "description": "Examine the recommended business models for your selected region and crops"
        },
        {
            "step": "5. Access Implementation Guides",
            "description": "Click 'View Implementation Guide' to get detailed information on your chosen business model"
        }
    ],
    "future_enhancements": [
        "Mobile application version for field use",
        "User accounts for saving preferences and tracking progress",
        "Integration with financing institutions for direct application",
        "Community features to connect with other youth entrepreneurs",
        "Real-time market price data integration"
    ],
    "technical_requirements": {
        "user_side": "Modern web browser with JavaScript enabled",
        "production_hosting": "Web server with database backend",
        "data_updates": "Monthly updates of market prices and intervention values"
    }
}